volara_torch/__init__.py
volara_torch/models.py
volara_torch/blockwise/__init__.py
volara_torch/blockwise/predict.py
volara_torch-1.0.1.dist-info/METADATA
volara_torch-1.0.1.dist-info/WHEEL
volara_torch-1.0.1.dist-info/entry_points.txt
volara_torch-1.0.1.dist-info/top_level.txt
volara_torch-1.0.1.dist-info/RECORD
